parq/__init__.py
parq/__main__.py
parq/cli.py
parq/output.py
parq/reader.py
parq_cli-0.1.0.dist-info/METADATA
parq_cli-0.1.0.dist-info/WHEEL
parq_cli-0.1.0.dist-info/entry_points.txt
parq_cli-0.1.0.dist-info/licenses/LICENSE
parq_cli-0.1.0.dist-info/RECORD
