Metadata-Version: 2.4
Name: parq-cli
Version: 0.1.0
Summary: A powerful command-line tool for inspecting and analyzing Apache Parquet files
Project-URL: Homepage, https://github.com/Tendo33/parq-cli
Project-URL: Repository, https://github.com/Tendo33/parq-cli
Project-URL: Issues, https://github.com/Tendo33/parq-cli/issues
Project-URL: Documentation, https://github.com/Tendo33/parq-cli#readme
Author-email: SimonSun <sjf19981112@gmail.com>
License: MIT
License-File: LICENSE
Keywords: analytics,apache-parquet,cli,data,data-tools,parquet
Classifier: Development Status :: 3 - Alpha
Classifier: Intended Audience :: Developers
Classifier: License :: OSI Approved :: MIT License
Classifier: Programming Language :: Python :: 3
Classifier: Programming Language :: Python :: 3.9
Classifier: Programming Language :: Python :: 3.10
Classifier: Programming Language :: Python :: 3.11
Classifier: Programming Language :: Python :: 3.12
Classifier: Programming Language :: Python :: 3.13
Requires-Python: >=3.9
Requires-Dist: pandas>=2.0.0
Requires-Dist: pyarrow>=18.0.0
Requires-Dist: rich>=13.0.0
Requires-Dist: typer>=0.15.0
Provides-Extra: dev
Requires-Dist: pytest-cov>=4.1.0; extra == 'dev'
Requires-Dist: pytest>=8.0.0; extra == 'dev'
Requires-Dist: ruff>=0.7.0; extra == 'dev'
